level1/mux4to1.v
module mux4to1(input [3:0] A, input [1:0] S, output reg Y);

always @(*) begin
    case(S)
        2'b00 : Y= A[0];
        2'b01 : Y= A[1];
        2'b10 : Y= A[2];
        2'b11 : Y= A[3];
    endcase
    end



endmodule

level1/mux4to1_tb.v
`timescale 1ns / 1ps
`include "mux4to1.v"


module mux4to1_tb;

    // Testbench signals
    reg [3:0] A;    // 4-bit input
    reg [1:0] S;    // 2-bit select
    wire Y;         // Output

    // Instantiate the Unit Under Test (UUT)
    mux4to1 uut (
        .A(A),
        .S(S),
        .Y(Y)
    );

    // Test all combinations
    initial begin
        $dumpfile("mux4to1.vcd");
        $dumpvars(0,mux4to1_tb);

        
        $display("Time\tA\tS\tY");
        $monitor("%0dns\t%b\t%b\t%b", $time, A, S, Y);

        // Apply test cases
        A = 4'b0000; S = 2'b00; #10;
        A = 4'b0001; S = 2'b01; #10;
        A = 4'b0010; S = 2'b10; #10;
        A = 4'b0011; S = 2'b11; #10;
        
        A = 4'b1100; S = 2'b00; #10;
        A = 4'b1010; S = 2'b01; #10;
        A = 4'b0101; S = 2'b10; #10;
        A = 4'b1111; S = 2'b11; #10;

        $finish;  // End simulation
    end

endmodule

level1/mux4to1.vcd
$date
	Thu Apr 24 13:02:26 2025
$end
$version
	Icarus Verilog
$end
$timescale
	1ps
$end
$scope module mux4to1_tb $end
$var wire 1 ! Y $end
$var reg 4 " A [3:0] $end
$var reg 2 # S [1:0] $end
$scope module uut $end
$var wire 4 $ A [3:0] $end
$var wire 2 % S [1:0] $end
$var reg 1 ! Y $end
$upscope $end
$upscope $end
$enddefinitions $end
$comment Show the parameter values. $end
$dumpall
$end
#0
$dumpvars
b0 %
b0 $
b0 #
b0 "
0!
$end
#10000
b1 #
b1 %
b1 "
b1 $
#20000
b10 #
b10 %
b10 "
b10 $
#30000
b11 #
b11 %
b11 "
b11 $
#40000
b0 #
b0 %
b1100 "
b1100 $
#50000
1!
b1 #
b1 %
b1010 "
b1010 $
#60000
b10 #
b10 %
b101 "
b101 $
#70000
b11 #
b11 %
b1111 "
b1111 $
